Metadata-Version: 2.1
Name: backports.strenum
Version: 1.1.1
Summary: Base class for creating enumerated constants that are also subclasses of str
Home-page: https://github.com/clbarnes/backports.strenum
License: UNKNOWN
Keywords: backports,enum,strenum
Platform: UNKNOWN
Classifier: Development Status :: 3 - Alpha
Classifier: Intended Audience :: Developers
Classifier: Programming Language :: Python :: 3
Classifier: Programming Language :: Python :: 3.8
Classifier: Programming Language :: Python :: 3.9
Classifier: Programming Language :: Python :: 3 :: Only
Requires-Python: >=3.8, <4
